CONTRIBUTING.rst
LICENSE.txt
MANIFEST.in
README.md
README.txt
VERSION
contribute.json
setup.cfg
setup.py
relengapi/__init__.py
relengapi/app.py
relengapi/celery.py
relengapi/cmd.py
relengapi.egg-info/PKG-INFO
relengapi.egg-info/SOURCES.txt
relengapi.egg-info/dependency_links.txt
relengapi.egg-info/entry_points.txt
relengapi.egg-info/not-zip-safe
relengapi.egg-info/requires.txt
relengapi.egg-info/top_level.txt
relengapi/alembic/relengapi/README
relengapi/alembic/relengapi/alembic.ini
relengapi/alembic/relengapi/env.py
relengapi/alembic/relengapi/script.py.mako
relengapi/alembic/relengapi/versions/993e4d841aa_.py
relengapi/alembic/templates/relengapi/README
relengapi/alembic/templates/relengapi/alembic.ini.mako
relengapi/alembic/templates/relengapi/env.py
relengapi/alembic/templates/relengapi/script.py.mako
relengapi/blueprints/__init__.py
relengapi/blueprints/archiver/__init__.py
relengapi/blueprints/archiver/tables.py
relengapi/blueprints/archiver/tasks.py
relengapi/blueprints/archiver/test_archiver.py
relengapi/blueprints/archiver/test_tasks.py
relengapi/blueprints/archiver/test_util.py
relengapi/blueprints/archiver/types.py
relengapi/blueprints/auth/__init__.py
relengapi/blueprints/auth/test_auth.py
relengapi/blueprints/auth/static/account.html
relengapi/blueprints/auth/static/account.js
relengapi/blueprints/badpenny/__init__.py
relengapi/blueprints/badpenny/cleanup.py
relengapi/blueprints/badpenny/cron.py
relengapi/blueprints/badpenny/execution.py
relengapi/blueprints/badpenny/rest.py
relengapi/blueprints/badpenny/tables.py
relengapi/blueprints/badpenny/test_badpenny.py
relengapi/blueprints/badpenny/static/badpenny.css
relengapi/blueprints/badpenny/static/badpenny.html
relengapi/blueprints/badpenny/static/badpenny.js
relengapi/blueprints/badpenny/static/bp-job.html
relengapi/blueprints/badpenny/static/bp-task.html
relengapi/blueprints/badpenny/static/statusIcon.html
relengapi/blueprints/badpenny/templates/badpenny_root_widget.html
relengapi/blueprints/base/__init__.py
relengapi/blueprints/base/alembic_wrapper.py
relengapi/blueprints/base/test_base.py
relengapi/blueprints/clobberer/__init__.py
relengapi/blueprints/clobberer/models.py
relengapi/blueprints/clobberer/rest.py
