Metadata-Version: 1.0
Name: relengapi
Version: 3.3.8
Summary: The code behind https://api.pub.build.mozilla.org
Home-page: https://api.pub.build.mozilla.org
Author: Dustin J. Mitchell
Author-email: dustin@mozilla.com
License: MPL2
Platform: UNKNOWN
